odoo/addons/server_action_navigate/README.rst
odoo/addons/server_action_navigate/__init__.py
odoo/addons/server_action_navigate/__manifest__.py
odoo/addons/server_action_navigate/demo/ir_actions_server.xml
odoo/addons/server_action_navigate/i18n/fr.po
odoo/addons/server_action_navigate/i18n/server_action_navigate.pot
odoo/addons/server_action_navigate/models/__init__.py
odoo/addons/server_action_navigate/models/ir_actions_server.py
odoo/addons/server_action_navigate/models/ir_actions_server_navigate_line.py
odoo/addons/server_action_navigate/readme/CONFIGURE.rst
odoo/addons/server_action_navigate/readme/CONTRIBUTORS.rst
odoo/addons/server_action_navigate/readme/DESCRIPTION.rst
odoo/addons/server_action_navigate/readme/USAGE.rst
odoo/addons/server_action_navigate/security/ir.model.access.csv
odoo/addons/server_action_navigate/static/description/icon.png
odoo/addons/server_action_navigate/static/description/index.html
odoo/addons/server_action_navigate/static/description/ir_actions_server_form.png
odoo/addons/server_action_navigate/static/description/product_product_tree.png
odoo/addons/server_action_navigate/static/description/sale_order_tree.png
odoo/addons/server_action_navigate/tests/__init__.py
odoo/addons/server_action_navigate/tests/test_module.py
odoo/addons/server_action_navigate/views/view_ir_actions_server.xml
odoo13_addon_server_action_navigate-13.0.1.0.1.dist-info/METADATA
odoo13_addon_server_action_navigate-13.0.1.0.1.dist-info/WHEEL
odoo13_addon_server_action_navigate-13.0.1.0.1.dist-info/top_level.txt
odoo13_addon_server_action_navigate-13.0.1.0.1.dist-info/RECORD
